{
  "$schema": "https://schemas.wp.org/trunk/block.json",
  "apiVersion": 2,
  "name": "x-s-d/faq-more-accordion",
  "version": "0.1.0",
  "title": "Faq More Accordion",
  "category": "widgets",
  "icon": "smiley",
  "description": "Example block scaffolded with Create Block tool.",
  "supports": {
    "html": false,
    "color": {
      "gradients": true
    }
  },
  "attributes": {
    "titol": {
      "type": "string"
    },
    "colorName": {
      "type": "string",
      "default": "base"
    },
    "markerColor": {
      "type": "string"
    },
    "customMarkerColor": {
      "type": "string"
    }
  },
  "textdomain": "faq-more-accordion",
  "editorScript": "file:./index.js",
  "editorStyle": "file:./index.css",
  "style": "file:./style-index.css",
  "render": "file:./render.php"
}